[
  {
    "id": "c34cea04-ccd3-41a9-bca7-d50a42d8d2c3",
    "data": [
      {
        "text": "basta",
        "userDefined": false
      }
    ],
    "isTemplate": false,
    "count": 0,
    "updated": 1539635589
  },
  {
    "id": "327b48d0-11ee-45a7-8678-2f23496ec192",
    "data": [
      {
        "text": "stop gioco",
        "userDefined": false
      }
    ],
    "isTemplate": false,
    "count": 1,
    "updated": 1539635589
  },
  {
    "id": "01c46186-397f-4423-b80f-9366bb534f66",
    "data": [
      {
        "text": "fine",
        "meta": "@sys.ignore",
        "userDefined": false
      },
      {
        "text": " gioco",
        "userDefined": false
      }
    ],
    "isTemplate": false,
    "count": 1,
    "updated": 1539635589
  },
  {
    "id": "52eb33b1-1038-44bb-ad4e-277749556606",
    "data": [
      {
        "text": "esci dall\u0027app",
        "userDefined": false
      }
    ],
    "isTemplate": false,
    "count": 0,
    "updated": 1539635589
  },
  {
    "id": "a6b0dfe4-0293-43f5-9359-e670b013ddbb",
    "data": [
      {
        "text": "esci",
        "userDefined": false
      }
    ],
    "isTemplate": false,
    "count": 0,
    "updated": 1539635589
  },
  {
    "id": "4e8aa351-1763-4407-9c57-c34cebeef4fe",
    "data": [
      {
        "text": "fine app",
        "userDefined": false
      }
    ],
    "isTemplate": false,
    "count": 0,
    "updated": 1539635589
  },
  {
    "id": "4c7473d7-4721-489e-affd-2ce4790e5e2e",
    "data": [
      {
        "text": "fine",
        "meta": "@sys.ignore",
        "userDefined": false
      }
    ],
    "isTemplate": false,
    "count": 0,
    "updated": 1539635589
  },
  {
    "id": "888521d5-be21-4600-a43e-d9a55951c57b",
    "data": [
      {
        "text": "a presto",
        "userDefined": false
      }
    ],
    "isTemplate": false,
    "count": 0,
    "updated": 1539635589
  },
  {
    "id": "1e792510-66bb-4576-a1ee-66dc1bc79f43",
    "data": [
      {
        "text": "esci dal gioco",
        "userDefined": false
      }
    ],
    "isTemplate": false,
    "count": 0,
    "updated": 1539635589
  },
  {
    "id": "cbe9ff3f-aeba-4b56-aad7-a7c6b89bef17",
    "data": [
      {
        "text": "stop",
        "userDefined": false
      }
    ],
    "isTemplate": false,
    "count": 0,
    "updated": 1539635589
  }
]